nautobot_design_builder/__init__.py
nautobot_design_builder/api/__init__.py
nautobot_design_builder/api/serializers.py
nautobot_design_builder/api/urls.py
nautobot_design_builder/api/views.py
nautobot_design_builder/app-config-schema.json
nautobot_design_builder/changes.py
nautobot_design_builder/choices.py
nautobot_design_builder/context.py
nautobot_design_builder/contrib/__init__.py
nautobot_design_builder/contrib/ext.py
nautobot_design_builder/contrib/tests/__init__.py
nautobot_design_builder/contrib/tests/test_ext.py
nautobot_design_builder/contrib/tests/testdata/bgp_extension.yaml
nautobot_design_builder/contrib/tests/testdata/cable_connections.yaml
nautobot_design_builder/contrib/tests/testdata/child_prefix.yaml
nautobot_design_builder/contrib/tests/testdata/lookup_extension.yaml
nautobot_design_builder/contrib/tests/testdata/next_prefix.yaml
nautobot_design_builder/contrib/tests/testdata/next_prefix_by_role_and_tenant.yaml
nautobot_design_builder/contrib/tests/testdata/next_prefix_for_location.yaml
nautobot_design_builder/custom_validators.py
nautobot_design_builder/debug.py
nautobot_design_builder/design.py
nautobot_design_builder/design_job.py
nautobot_design_builder/errors.py
nautobot_design_builder/ext.py
nautobot_design_builder/fields.py
nautobot_design_builder/filters.py
nautobot_design_builder/forms.py
nautobot_design_builder/git.py
nautobot_design_builder/helpers.py
nautobot_design_builder/jinja2.py
nautobot_design_builder/jinja_filters.py
nautobot_design_builder/jobs.py
nautobot_design_builder/management/__init__.py
nautobot_design_builder/management/commands/__init__.py
nautobot_design_builder/management/commands/build_design.py
nautobot_design_builder/management/commands/install_demo_designs.py
nautobot_design_builder/middleware.py
nautobot_design_builder/migrations/0001_initial.py
nautobot_design_builder/migrations/0002_nautobot_v2.py
nautobot_design_builder/migrations/__init__.py
nautobot_design_builder/models.py
nautobot_design_builder-2.2.0.dist-info/LICENSE
nautobot_design_builder-2.2.0.dist-info/METADATA
nautobot_design_builder-2.2.0.dist-info/WHEEL
nautobot_design_builder-2.2.0.dist-info/RECORD
