Metadata-Version: 2.3
Name: nautobot-design-builder
Version: 2.2.0
Summary: Nautobot app that uses design templates to easily create data objects in Nautobot with minimal input from a user.
License: Apache-2.0
Keywords: nautobot,nautobot-plugin
Author: Network to Code, LLC
Author-email: opensource@networktocode.com
Requires-Python: >=3.8.1,<3.13
Classifier: Development Status :: 5 - Production/Stable
Classifier: Intended Audience :: Developers
Classifier: License :: OSI Approved :: Apache Software License
Classifier: Programming Language :: Python :: 3
Classifier: Programming Language :: Python :: 3.9
Classifier: Programming Language :: Python :: 3.10
Classifier: Programming Language :: Python :: 3.11
Classifier: Programming Language :: Python :: 3.12
Classifier: Programming Language :: Python :: 3.8
Requires-Dist: nautobot (>=2.0.3,<3.0)
Project-URL: Homepage, https://github.com/nautobot/nautobot-app-design-builder
Project-URL: Repository, https://github.com/nautobot/nautobot-app-design-builder
